gdphelper/__init__.py
gdphelper/gdpcleaner.py
gdphelper/gdpdescribe.py
gdphelper/gdpimporter.py
gdphelper/gdpplotter.py
gdphelper-1.1.11.dist-info/LICENSE
gdphelper-1.1.11.dist-info/WHEEL
gdphelper-1.1.11.dist-info/METADATA
gdphelper-1.1.11.dist-info/RECORD
