Metadata-Version: 2.1
Name: gdphelper
Version: 1.1.11
Summary: A package for streamlining EDA processes for basic Data Analysis
License: MIT
Author: Aldo Barros, Gabriel Fairbrother, Ramiro Mejia, Wanying Ye
Requires-Python: >=3.9,<4.0
Classifier: License :: OSI Approved :: MIT License
Classifier: Programming Language :: Python :: 3
Classifier: Programming Language :: Python :: 3.10
Classifier: Programming Language :: Python :: 3.9
Requires-Dist: ipykernel (>=6.7.0,<7.0.0)
Requires-Dist: matplotlib (>=3.5.1,<4.0.0)
Requires-Dist: numpy (>=1.22.1,<2.0.0)
Requires-Dist: pandas (>=1.3.5,<2.0.0)
Requires-Dist: requests (>=2.27.1,<3.0.0)
